Workbook

Sheet Dashboard
A1: WEEKLY GLOBAL MACRO MONITOR | S1: Week Ending:
A2: Country Indicator Heatmap | S2: Prepared by: | T2: Research & Strategy
A4: Category | B4: Indicator | C4: Unit | D4: 🇺🇸 USA | E4: ▼ / ▲ / ↔ | F4: 🇪🇺 EUR | G4: ▼ / ▲ / ↔ | H4: 🇸🇬 SGP | I4: ▼ / ▲ / ↔ | J4: 🇨🇳 CHN | K4: ▼ / ▲ / ↔ | L4: 🇮🇳 IND | M4: ▼ / ▲ / ↔ | N4: 🇱🇰 LKA | O4: ▼ / ▲ / ↔ | P4: Freq. | Q4: Latest Date
A5: GROWTH | B5: GDP Growth (YoY %) | C5: % YoY | D5: =IF(ISNUMBER(Data!D5),Data!D5,"n/a") -> n/a | E5: =IF(AND(ISNUMBER(Data!D5),ISNUMBER(Data!E5)),IF(Data!D5>Data!E5,"▲",IF(Data!D5<Data!E5,"▼","↔")),"-") -> - | F5: =IF(ISNUMBER(Data!F5),Data!F5,"n/a") -> n/a | G5: =IF(AND(ISNUMBER(Data!F5),ISNUMBER(Data!G5)),IF(Data!F5>Data!G5,"▲",IF(Data!F5<Data!G5,"▼","↔")),"-") -> - | H5: =IF(ISNUMBER(Data!H5),Data!H5,"n/a") -> n/a | I5: =IF(AND(ISNUMBER(Data!H5),ISNUMBER(Data!I5)),IF(Data!H5>Data!I5,"▲",IF(Data!H5<Data!I5,"▼","↔")),"-") -> - | J5: =IF(ISNUMBER(Data!J5),Data!J5,"n/a") -> n/a | K5: =IF(AND(ISNUMBER(Data!J5),ISNUMBER(Data!K5)),IF(Data!J5>Data!K5,"▲",IF(Data!J5<Data!K5,"▼","↔")),"-") -> - | L5: =IF(ISNUMBER(Data!L5),Data!L5,"n/a") -> n/a | M5: =IF(AND(ISNUMBER(Data!L5),ISNUMBER(Data!M5)),IF(Data!L5>Data!M5,"▲",IF(Data!L5<Data!M5,"▼","↔")),"-") -> - | N5: =IF(ISNUMBER(Data!N5),Data!N5,"n/a") -> n/a | O5: =IF(AND(ISNUMBER(Data!N5),ISNUMBER(Data!O5)),IF(Data!N5>Data!O5,"▲",IF(Data!N5<Data!O5,"▼","↔")),"-") -> - | P5: =Data!P5 -> Quarterly
A6: GROWTH | B6: Manufacturing PMI | C6: Index | D6: =IF(ISNUMBER(Data!D6),Data!D6,"n/a") -> n/a | E6: =IF(AND(ISNUMBER(Data!D6),ISNUMBER(Data!E6)),IF(Data!D6>Data!E6,"▲",IF(Data!D6<Data!E6,"▼","↔")),"-") -> - | F6: =IF(ISNUMBER(Data!F6),Data!F6,"n/a") -> n/a | G6: =IF(AND(ISNUMBER(Data!F6),ISNUMBER(Data!G6)),IF(Data!F6>Data!G6,"▲",IF(Data!F6<Data!G6,"▼","↔")),"-") -> - | H6: =IF(ISNUMBER(Data!H6),Data!H6,"n/a") -> n/a | I6: =IF(AND(ISNUMBER(Data!H6),ISNUMBER(Data!I6)),IF(Data!H6>Data!I6,"▲",IF(Data!H6<Data!I6,"▼","↔")),"-") -> - | J6: =IF(ISNUMBER(Data!J6),Data!J6,"n/a") -> n/a | K6: =IF(AND(ISNUMBER(Data!J6),ISNUMBER(Data!K6)),IF(Data!J6>Data!K6,"▲",IF(Data!J6<Data!K6,"▼","↔")),"-") -> - | L6: =IF(ISNUMBER(Data!L6),Data!L6,"n/a") -> n/a | M6: =IF(AND(ISNUMBER(Data!L6),ISNUMBER(Data!M6)),IF(Data!L6>Data!M6,"▲",IF(Data!L6<Data!M6,"▼","↔")),"-") -> - | N6: =IF(ISNUMBER(Data!N6),Data!N6,"n/a") -> n/a | O6: =IF(AND(ISNUMBER(Data!N6),ISNUMBER(Data!O6)),IF(Data!N6>Data!O6,"▲",IF(Data!N6<Data!O6,"▼","↔")),"-") -> - | P6: =Data!P6 -> Monthly (1st week)
A7: GROWTH | B7: Services PMI | C7: Index | D7: =IF(ISNUMBER(Data!D7),Data!D7,"n/a") -> n/a | E7: =IF(AND(ISNUMBER(Data!D7),ISNUMBER(Data!E7)),IF(Data!D7>Data!E7,"▲",IF(Data!D7<Data!E7,"▼","↔")),"-") -> - | F7: =IF(ISNUMBER(Data!F7),Data!F7,"n/a") -> n/a | G7: =IF(AND(ISNUMBER(Data!F7),ISNUMBER(Data!G7)),IF(Data!F7>Data!G7,"▲",IF(Data!F7<Data!G7,"▼","↔")),"-") -> - | H7: =IF(ISNUMBER(Data!H7),Data!H7,"n/a") -> n/a | I7: =IF(AND(ISNUMBER(Data!H7),ISNUMBER(Data!I7)),IF(Data!H7>Data!I7,"▲",IF(Data!H7<Data!I7,"▼","↔")),"-") -> - | J7: =IF(ISNUMBER(Data!J7),Data!J7,"n/a") -> n/a | K7: =IF(AND(ISNUMBER(Data!J7),ISNUMBER(Data!K7)),IF(Data!J7>Data!K7,"▲",IF(Data!J7<Data!K7,"▼","↔")),"-") -> - | L7: =IF(ISNUMBER(Data!L7),Data!L7,"n/a") -> n/a | M7: =IF(AND(ISNUMBER(Data!L7),ISNUMBER(Data!M7)),IF(Data!L7>Data!M7,"▲",IF(Data!L7<Data!M7,"▼","↔")),"-") -> - | N7: =IF(ISNUMBER(Data!N7),Data!N7,"n/a") -> n/a | O7: =IF(AND(ISNUMBER(Data!N7),ISNUMBER(Data!O7)),IF(Data!N7>Data!O7,"▲",IF(Data!N7<Data!O7,"▼","↔")),"-") -> - | P7: =Data!P7 -> Monthly (1st week)
A8: GROWTH | B8: Industrial Production (YoY %) | C8: % YoY | D8: =IF(ISNUMBER(Data!D8),Data!D8,"n/a") -> n/a | E8: =IF(AND(ISNUMBER(Data!D8),ISNUMBER(Data!E8)),IF(Data!D8>Data!E8,"▲",IF(Data!D8<Data!E8,"▼","↔")),"-") -> - | F8: =IF(ISNUMBER(Data!F8),Data!F8,"n/a") -> n/a | G8: =IF(AND(ISNUMBER(Data!F8),ISNUMBER(Data!G8)),IF(Data!F8>Data!G8,"▲",IF(Data!F8<Data!G8,"▼","↔")),"-") -> - | H8: =IF(ISNUMBER(Data!H8),Data!H8,"n/a") -> n/a | I8: =IF(AND(ISNUMBER(Data!H8),ISNUMBER(Data!I8)),IF(Data!H8>Data!I8,"▲",IF(Data!H8<Data!I8,"▼","↔")),"-") -> - | J8: =IF(ISNUMBER(Data!J8),Data!J8,"n/a") -> n/a | K8: =IF(AND(ISNUMBER(Data!J8),ISNUMBER(Data!K8)),IF(Data!J8>Data!K8,"▲",IF(Data!J8<Data!K8,"▼","↔")),"-") -> - | L8: =IF(ISNUMBER(Data!L8),Data!L8,"n/a") -> n/a | M8: =IF(AND(ISNUMBER(Data!L8),ISNUMBER(Data!M8)),IF(Data!L8>Data!M8,"▲",IF(Data!L8<Data!M8,"▼","↔")),"-") -> - | N8: =IF(ISNUMBER(Data!N8),Data!N8,"n/a") -> n/a | O8: =IF(AND(ISNUMBER(Data!N8),ISNUMBER(Data!O8)),IF(Data!N8>Data!O8,"▲",IF(Data!N8<Data!O8,"▼","↔")),"-") -> - | P8: =Data!P8 -> Monthly
A9: INFLATION | B9: Headline CPI (YoY %) | C9: % YoY | D9: =IF(ISNUMBER(Data!D9),Data!D9,"n/a") -> n/a | E9: =IF(AND(ISNUMBER(Data!D9),ISNUMBER(Data!E9)),IF(Data!D9>Data!E9,"▲",IF(Data!D9<Data!E9,"▼","↔")),"-") -> - | F9: =IF(ISNUMBER(Data!F9),Data!F9,"n/a") -> n/a | G9: =IF(AND(ISNUMBER(Data!F9),ISNUMBER(Data!G9)),IF(Data!F9>Data!G9,"▲",IF(Data!F9<Data!G9,"▼","↔")),"-") -> - | H9: =IF(ISNUMBER(Data!H9),Data!H9,"n/a") -> n/a | I9: =IF(AND(ISNUMBER(Data!H9),ISNUMBER(Data!I9)),IF(Data!H9>Data!I9,"▲",IF(Data!H9<Data!I9,"▼","↔")),"-") -> - | J9: =IF(ISNUMBER(Data!J9),Data!J9,"n/a") -> n/a | K9: =IF(AND(ISNUMBER(Data!J9),ISNUMBER(Data!K9)),IF(Data!J9>Data!K9,"▲",IF(Data!J9<Data!K9,"▼","↔")),"-") -> - | L9: =IF(ISNUMBER(Data!L9),Data!L9,"n/a") -> n/a | M9: =IF(AND(ISNUMBER(Data!L9),ISNUMBER(Data!M9)),IF(Data!L9>Data!M9,"▲",IF(Data!L9<Data!M9,"▼","↔")),"-") -> - | N9: =IF(ISNUMBER(Data!N9),Data!N9,"n/a") -> n/a | O9: =IF(AND(ISNUMBER(Data!N9),ISNUMBER(Data!O9)),IF(Data!N9>Data!O9,"▲",IF(Data!N9<Data!O9,"▼","↔")),"-") -> - | P9: =Data!P9 -> Monthly (2nd week)
A10: INFLATION | B10: Core CPI (YoY %) | C10: % YoY | D10: =IF(ISNUMBER(Data!D10),Data!D10,"n/a") -> n/a | E10: =IF(AND(ISNUMBER(Data!D10),ISNUMBER(Data!E10)),IF(Data!D10>Data!E10,"▲",IF(Data!D10<Data!E10,"▼","↔")),"-") -> - | F10: =IF(ISNUMBER(Data!F10),Data!F10,"n/a") -> n/a | G10: =IF(AND(ISNUMBER(Data!F10),ISNUMBER(Data!G10)),IF(Data!F10>Data!G10,"▲",IF(Data!F10<Data!G10,"▼","↔")),"-") -> - | H10: =IF(ISNUMBER(Data!H10),Data!H10,"n/a") -> n/a | I10: =IF(AND(ISNUMBER(Data!H10),ISNUMBER(Data!I10)),IF(Data!H10>Data!I10,"▲",IF(Data!H10<Data!I10,"▼","↔")),"-") -> - | J10: =IF(ISNUMBER(Data!J10),Data!J10,"n/a") -> n/a | K10: =IF(AND(ISNUMBER(Data!J10),ISNUMBER(Data!K10)),IF(Data!J10>Data!K10,"▲",IF(Data!J10<Data!K10,"▼","↔")),"-") -> - | L10: =IF(ISNUMBER(Data!L10),Data!L10,"n/a") -> n/a | M10: =IF(AND(ISNUMBER(Data!L10),ISNUMBER(Data!M10)),IF(Data!L10>Data!M10,"▲",IF(Data!L10<Data!M10,"▼","↔")),"-") -> - | N10: =IF(ISNUMBER(Data!N10),Data!N10,"n/a") -> n/a | O10: =IF(AND(ISNUMBER(Data!N10),ISNUMBER(Data!O10)),IF(Data!N10>Data!O10,"▲",IF(Data!N10<Data!O10,"▼","↔")),"-") -> - | P10: =Data!P10 -> Monthly
A11: INFLATION | B11: Food Inflation (YoY %) | C11: % YoY | D11: =IF(ISNUMBER(Data!D11),Data!D11,"n/a") -> n/a | E11: =IF(AND(ISNUMBER(Data!D11),ISNUMBER(Data!E11)),IF(Data!D11>Data!E11,"▲",IF(Data!D11<Data!E11,"▼","↔")),"-") -> - | F11: =IF(ISNUMBER(Data!F11),Data!F11,"n/a") -> n/a | G11: =IF(AND(ISNUMBER(Data!F11),ISNUMBER(Data!G11)),IF(Data!F11>Data!G11,"▲",IF(Data!F11<Data!G11,"▼","↔")),"-") -> - | H11: =IF(ISNUMBER(Data!H11),Data!H11,"n/a") -> n/a | I11: =IF(AND(ISNUMBER(Data!H11),ISNUMBER(Data!I11)),IF(Data!H11>Data!I11,"▲",IF(Data!H11<Data!I11,"▼","↔")),"-") -> - | J11: =IF(ISNUMBER(Data!J11),Data!J11,"n/a") -> n/a | K11: =IF(AND(ISNUMBER(Data!J11),ISNUMBER(Data!K11)),IF(Data!J11>Data!K11,"▲",IF(Data!J11<Data!K11,"▼","↔")),"-") -> - | L11: =IF(ISNUMBER(Data!L11),Data!L11,"n/a") -> n/a | M11: =IF(AND(ISNUMBER(Data!L11),ISNUMBER(Data!M11)),IF(Data!L11>Data!M11,"▲",IF(Data!L11<Data!M11,"▼","↔")),"-") -> - | N11: =IF(ISNUMBER(Data!N11),Data!N11,"n/a") -> n/a | O11: =IF(AND(ISNUMBER(Data!N11),ISNUMBER(Data!O11)),IF(Data!N11>Data!O11,"▲",IF(Data!N11<Data!O11,"▼","↔")),"-") -> - | P11: =Data!P11 -> Monthly
A12: MONETARY | B12: Policy Rate (%) | C12: % | D12: =IF(ISNUMBER(Data!D12),Data!D12,"n/a") -> n/a | E12: =IF(AND(ISNUMBER(Data!D12),ISNUMBER(Data!E12)),IF(Data!D12>Data!E12,"▲",IF(Data!D12<Data!E12,"▼","↔")),"-") -> - | F12: =IF(ISNUMBER(Data!F12),Data!F12,"n/a") -> n/a | G12: =IF(AND(ISNUMBER(Data!F12),ISNUMBER(Data!G12)),IF(Data!F12>Data!G12,"▲",IF(Data!F12<Data!G12,"▼","↔")),"-") -> - | H12: =IF(ISNUMBER(Data!H12),Data!H12,"n/a") -> n/a | I12: =IF(AND(ISNUMBER(Data!H12),ISNUMBER(Data!I12)),IF(Data!H12>Data!I12,"▲",IF(Data!H12<Data!I12,"▼","↔")),"-") -> - | J12: =IF(ISNUMBER(Data!J12),Data!J12,"n/a") -> n/a | K12: =IF(AND(ISNUMBER(Data!J12),ISNUMBER(Data!K12)),IF(Data!J12>Data!K12,"▲",IF(Data!J12<Data!K12,"▼","↔")),"-") -> - | L12: =IF(ISNUMBER(Data!L12),Data!L12,"n/a") -> n/a | M12: =IF(AND(ISNUMBER(Data!L12),ISNUMBER(Data!M12)),IF(Data!L12>Data!M12,"▲",IF(Data!L12<Data!M12,"▼","↔")),"-") -> - | N12: =IF(ISNUMBER(Data!N12),Data!N12,"n/a") -> n/a | O12: =IF(AND(ISNUMBER(Data!N12),ISNUMBER(Data!O12)),IF(Data!N12>Data!O12,"▲",IF(Data!N12<Data!O12,"▼","↔")),"-") -> - | P12: =Data!P12 -> Per meeting
A13: MONETARY | B13: 10Y Bond Yield (%) | C13: % | D13: =IF(ISNUMBER(Data!D13),Data!D13,"n/a") -> n/a | E13: =IF(AND(ISNUMBER(Data!D13),ISNUMBER(Data!E13)),IF(Data!D13>Data!E13,"▲",IF(Data!D13<Data!E13,"▼","↔")),"-") -> - | F13: =IF(ISNUMBER(Data!F13),Data!F13,"n/a") -> n/a | G13: =IF(AND(ISNUMBER(Data!F13),ISNUMBER(Data!G13)),IF(Data!F13>Data!G13,"▲",IF(Data!F13<Data!G13,"▼","↔")),"-") -> - | H13: =IF(ISNUMBER(Data!H13),Data!H13,"n/a") -> n/a | I13: =IF(AND(ISNUMBER(Data!H13),ISNUMBER(Data!I13)),IF(Data!H13>Data!I13,"▲",IF(Data!H13<Data!I13,"▼","↔")),"-") -> - | J13: =IF(ISNUMBER(Data!J13),Data!J13,"n/a") -> n/a | K13: =IF(AND(ISNUMBER(Data!J13),ISNUMBER(Data!K13)),IF(Data!J13>Data!K13,"▲",IF(Data!J13<Data!K13,"▼","↔")),"-") -> - | L13: =IF(ISNUMBER(Data!L13),Data!L13,"n/a") -> n/a | M13: =IF(AND(ISNUMBER(Data!L13),ISNUMBER(Data!M13)),IF(Data!L13>Data!M13,"▲",IF(Data!L13<Data!M13,"▼","↔")),"-") -> - | N13: =IF(ISNUMBER(Data!N13),Data!N13,"n/a") -> n/a | O13: =IF(AND(ISNUMBER(Data!N13),ISNUMBER(Data!O13)),IF(Data!N13>Data!O13,"▲",IF(Data!N13<Data!O13,"▼","↔")),"-") -> - | P13: =Data!P13 -> Weekly (Friday)
A14: MONETARY | B14: Yield Curve (10Y−2Y, bps) | C14: bps | D14: =IF(ISNUMBER(Data!D14),Data!D14,"n/a") -> n/a | E14: =IF(AND(ISNUMBER(Data!D14),ISNUMBER(Data!E14)),IF(Data!D14>Data!E14,"▲",IF(Data!D14<Data!E14,"▼","↔")),"-") -> - | F14: =IF(ISNUMBER(Data!F14),Data!F14,"n/a") -> n/a | G14: =IF(AND(ISNUMBER(Data!F14),ISNUMBER(Data!G14)),IF(Data!F14>Data!G14,"▲",IF(Data!F14<Data!G14,"▼","↔")),"-") -> - | H14: =IF(ISNUMBER(Data!H14),Data!H14,"n/a") -> n/a | I14: =IF(AND(ISNUMBER(Data!H14),ISNUMBER(Data!I14)),IF(Data!H14>Data!I14,"▲",IF(Data!H14<Data!I14,"▼","↔")),"-") -> - | J14: =IF(ISNUMBER(Data!J14),Data!J14,"n/a") -> n/a | K14: =IF(AND(ISNUMBER(Data!J14),ISNUMBER(Data!K14)),IF(Data!J14>Data!K14,"▲",IF(Data!J14<Data!K14,"▼","↔")),"-") -> - | L14: =IF(ISNUMBER(Data!L14),Data!L14,"n/a") -> n/a | M14: =IF(AND(ISNUMBER(Data!L14),ISNUMBER(Data!M14)),IF(Data!L14>Data!M14,"▲",IF(Data!L14<Data!M14,"▼","↔")),"-") -> - | N14: =IF(ISNUMBER(Data!N14),Data!N14,"n/a") -> n/a | O14: =IF(AND(ISNUMBER(Data!N14),ISNUMBER(Data!O14)),IF(Data!N14>Data!O14,"▲",IF(Data!N14<Data!O14,"▼","↔")),"-") -> - | P14: =Data!P14 -> Weekly
A15: LABOUR | B15: Unemployment Rate (%) | C15: % | D15: =IF(ISNUMBER(Data!D15),Data!D15,"n/a") -> n/a | E15: =IF(AND(ISNUMBER(Data!D15),ISNUMBER(Data!E15)),IF(Data!D15>Data!E15,"▲",IF(Data!D15<Data!E15,"▼","↔")),"-") -> - | F15: =IF(ISNUMBER(Data!F15),Data!F15,"n/a") -> n/a | G15: =IF(AND(ISNUMBER(Data!F15),ISNUMBER(Data!G15)),IF(Data!F15>Data!G15,"▲",IF(Data!F15<Data!G15,"▼","↔")),"-") -> - | H15: =IF(ISNUMBER(Data!H15),Data!H15,"n/a") -> n/a | I15: =IF(AND(ISNUMBER(Data!H15),ISNUMBER(Data!I15)),IF(Data!H15>Data!I15,"▲",IF(Data!H15<Data!I15,"▼","↔")),"-") -> - | J15: =IF(ISNUMBER(Data!J15),Data!J15,"n/a") -> n/a | K15: =IF(AND(ISNUMBER(Data!J15),ISNUMBER(Data!K15)),IF(Data!J15>Data!K15,"▲",IF(Data!J15<Data!K15,"▼","↔")),"-") -> - | L15: =IF(ISNUMBER(Data!L15),Data!L15,"n/a") -> n/a | M15: =IF(AND(ISNUMBER(Data!L15),ISNUMBER(Data!M15)),IF(Data!L15>Data!M15,"▲",IF(Data!L15<Data!M15,"▼","↔")),"-") -> - | N15: =IF(ISNUMBER(Data!N15),Data!N15,"n/a") -> n/a | O15: =IF(AND(ISNUMBER(Data!N15),ISNUMBER(Data!O15)),IF(Data!N15>Data!O15,"▲",IF(Data!N15<Data!O15,"▼","↔")),"-") -> - | P15: =Data!P15 -> Monthly
A16: LABOUR | B16: Wage Growth (YoY %) | C16: % YoY | D16: =IF(ISNUMBER(Data!D16),Data!D16,"n/a") -> n/a | E16: =IF(AND(ISNUMBER(Data!D16),ISNUMBER(Data!E16)),IF(Data!D16>Data!E16,"▲",IF(Data!D16<Data!E16,"▼","↔")),"-") -> - | F16: =IF(ISNUMBER(Data!F16),Data!F16,"n/a") -> n/a | G16: =IF(AND(ISNUMBER(Data!F16),ISNUMBER(Data!G16)),IF(Data!F16>Data!G16,"▲",IF(Data!F16<Data!G16,"▼","↔")),"-") -> - | H16: =IF(ISNUMBER(Data!H16),Data!H16,"n/a") -> n/a | I16: =IF(AND(ISNUMBER(Data!H16),ISNUMBER(Data!I16)),IF(Data!H16>Data!I16,"▲",IF(Data!H16<Data!I16,"▼","↔")),"-") -> - | J16: =IF(ISNUMBER(Data!J16),Data!J16,"n/a") -> n/a | K16: =IF(AND(ISNUMBER(Data!J16),ISNUMBER(Data!K16)),IF(Data!J16>Data!K16,"▲",IF(Data!J16<Data!K16,"▼","↔")),"-") -> - | L16: =IF(ISNUMBER(Data!L16),Data!L16,"n/a") -> n/a | M16: =IF(AND(ISNUMBER(Data!L16),ISNUMBER(Data!M16)),IF(Data!L16>Data!M16,"▲",IF(Data!L16<Data!M16,"▼","↔")),"-") -> - | N16: =IF(ISNUMBER(Data!N16),Data!N16,"n/a") -> n/a | O16: =IF(AND(ISNUMBER(Data!N16),ISNUMBER(Data!O16)),IF(Data!N16>Data!O16,"▲",IF(Data!N16<Data!O16,"▼","↔")),"-") -> - | P16: =Data!P16 -> Monthly/Quarterly
A17: MARKETS | B17: Equity Index (WoW %) | C17: % WoW | D17: =IF(ISNUMBER(Data!D17),Data!D17,"n/a") -> n/a | E17: =IF(AND(ISNUMBER(Data!D17),ISNUMBER(Data!E17)),IF(Data!D17>0,"▲",IF(Data!D17<0,"▼","↔")),"-") -> - | F17: =IF(ISNUMBER(Data!F17),Data!F17,"n/a") -> n/a | G17: =IF(AND(ISNUMBER(Data!F17),ISNUMBER(Data!G17)),IF(Data!F17>0,"▲",IF(Data!F17<0,"▼","↔")),"-") -> - | H17: =IF(ISNUMBER(Data!H17),Data!H17,"n/a") -> n/a | I17: =IF(ISNUMBER(Data!H17),IF(Data!H17>0,"▲",IF(Data!H17<0,"▼","↔")),"-") -> - | J17: =IF(ISNUMBER(Data!J17),Data!J17,"n/a") -> n/a | K17: =IF(ISNUMBER(Data!J17),IF(Data!J17>0,"▲",IF(Data!J17<0,"▼","↔")),"-") -> - | L17: =IF(ISNUMBER(Data!L17),Data!L17,"n/a") -> n/a | M17: =IF(ISNUMBER(Data!L17),IF(Data!L17>0,"▲",IF(Data!L17<0,"▼","↔")),"-") -> - | N17: =IF(ISNUMBER(Data!N17),Data!N17,"n/a") -> n/a | O17: =IF(ISNUMBER(Data!N17),IF(Data!N17>0,"▲",IF(Data!N17<0,"▼","↔")),"-") -> - | P17: =Data!P17 -> Weekly (Friday)
A18: MARKETS | B18: FX vs USD (WoW %) | C18: % WoW | D18: =IF(ISNUMBER(Data!D18),Data!D18,"n/a") -> n/a | E18: =IF(ISNUMBER(Data!D18),IF(Data!D18>0,"▲",IF(Data!D18<0,"▼","↔")),"-") -> - | F18: =IF(ISNUMBER(Data!F18),Data!F18,"n/a") -> n/a | G18: =IF(ISNUMBER(Data!F18),IF(Data!F18>0,"▲",IF(Data!F18<0,"▼","↔")),"-") -> - | H18: =IF(ISNUMBER(Data!H18),Data!H18,"n/a") -> n/a | I18: =IF(ISNUMBER(Data!H18),IF(Data!H18>0,"▲",IF(Data!H18<0,"▼","↔")),"-") -> - | J18: =IF(ISNUMBER(Data!J18),Data!J18,"n/a") -> n/a | K18: =IF(ISNUMBER(Data!J18),IF(Data!J18>0,"▲",IF(Data!J18<0,"▼","↔")),"-") -> - | L18: =IF(ISNUMBER(Data!L18),Data!L18,"n/a") -> n/a | M18: =IF(ISNUMBER(Data!L18),IF(Data!L18>0,"▲",IF(Data!L18<0,"▼","↔")),"-") -> - | N18: =IF(ISNUMBER(Data!N18),Data!N18,"n/a") -> n/a | O18: =IF(ISNUMBER(Data!N18),IF(Data!N18>0,"▲",IF(Data!N18<0,"▼","↔")),"-") -> - | P18: =Data!P18 -> Weekly
A19: MARKETS | B19: Credit Spreads/CDS (bps) | C19: bps | D19: =IF(ISNUMBER(Data!D19),Data!D19,"n/a") -> n/a | E19: =IF(AND(ISNUMBER(Data!D19),ISNUMBER(Data!E19)),IF(Data!D19>Data!E19,"▲",IF(Data!D19<Data!E19,"▼","↔")),"-") -> - | F19: =IF(ISNUMBER(Data!F19),Data!F19,"n/a") -> n/a | G19: =IF(AND(ISNUMBER(Data!F19),ISNUMBER(Data!G19)),IF(Data!F19>Data!G19,"▲",IF(Data!F19<Data!G19,"▼","↔")),"-") -> - | H19: =IF(ISNUMBER(Data!H19),Data!H19,"n/a") -> n/a | I19: =IF(AND(ISNUMBER(Data!H19),ISNUMBER(Data!I19)),IF(Data!H19>Data!I19,"▲",IF(Data!H19<Data!I19,"▼","↔")),"-") -> - | J19: =IF(ISNUMBER(Data!J19),Data!J19,"n/a") -> n/a | K19: =IF(AND(ISNUMBER(Data!J19),ISNUMBER(Data!K19)),IF(Data!J19>Data!K19,"▲",IF(Data!J19<Data!K19,"▼","↔")),"-") -> - | L19: =IF(ISNUMBER(Data!L19),Data!L19,"n/a") -> n/a | M19: =IF(AND(ISNUMBER(Data!L19),ISNUMBER(Data!M19)),IF(Data!L19>Data!M19,"▲",IF(Data!L19<Data!M19,"▼","↔")),"-") -> - | N19: =IF(ISNUMBER(Data!N19),Data!N19,"n/a") -> n/a | O19: =IF(AND(ISNUMBER(Data!N19),ISNUMBER(Data!O19)),IF(Data!N19>Data!O19,"▲",IF(Data!N19<Data!O19,"▼","↔")),"-") -> - | P19: =Data!P19 -> Weekly
A20: EXTERNAL | B20: Trade Balance (USD bn) | C20: USD bn | D20: =IF(ISNUMBER(Data!D20),Data!D20,"n/a") -> n/a | E20: =IF(AND(ISNUMBER(Data!D20),ISNUMBER(Data!E20)),IF(Data!D20>Data!E20,"▲",IF(Data!D20<Data!E20,"▼","↔")),"-") -> - | F20: =IF(ISNUMBER(Data!F20),Data!F20,"n/a") -> n/a | G20: =IF(AND(ISNUMBER(Data!F20),ISNUMBER(Data!G20)),IF(Data!F20>Data!G20,"▲",IF(Data!F20<Data!G20,"▼","↔")),"-") -> - | H20: =IF(ISNUMBER(Data!H20),Data!H20,"n/a") -> n/a | I20: =IF(AND(ISNUMBER(Data!H20),ISNUMBER(Data!I20)),IF(Data!H20>Data!I20,"▲",IF(Data!H20<Data!I20,"▼","↔")),"-") -> - | J20: =IF(ISNUMBER(Data!J20),Data!J20,"n/a") -> n/a | K20: =IF(AND(ISNUMBER(Data!J20),ISNUMBER(Data!K20)),IF(Data!J20>Data!K20,"▲",IF(Data!J20<Data!K20,"▼","↔")),"-") -> - | L20: =IF(ISNUMBER(Data!L20),Data!L20,"n/a") -> n/a | M20: =IF(AND(ISNUMBER(Data!L20),ISNUMBER(Data!M20)),IF(Data!L20>Data!M20,"▲",IF(Data!L20<Data!M20,"▼","↔")),"-") -> - | N20: =IF(ISNUMBER(Data!N20),Data!N20,"n/a") -> n/a | O20: =IF(AND(ISNUMBER(Data!N20),ISNUMBER(Data!O20)),IF(Data!N20>Data!O20,"▲",IF(Data!N20<Data!O20,"▼","↔")),"-") -> - | P20: =Data!P20 -> Monthly
A21: EXTERNAL | B21: FX Reserves (USD bn) | C21: USD bn | D21: =IF(ISNUMBER(Data!D21),Data!D21,"n/a") -> n/a | E21: =IF(AND(ISNUMBER(Data!D21),ISNUMBER(Data!E21)),IF(Data!D21>Data!E21,"▲",IF(Data!D21<Data!E21,"▼","↔")),"-") -> - | F21: =IF(ISNUMBER(Data!F21),Data!F21,"n/a") -> n/a | G21: =IF(AND(ISNUMBER(Data!F21),ISNUMBER(Data!G21)),IF(Data!F21>Data!G21,"▲",IF(Data!F21<Data!G21,"▼","↔")),"-") -> - | H21: =IF(ISNUMBER(Data!H21),Data!H21,"n/a") -> n/a | I21: =IF(AND(ISNUMBER(Data!H21),ISNUMBER(Data!I21)),IF(Data!H21>Data!I21,"▲",IF(Data!H21<Data!I21,"▼","↔")),"-") -> - | J21: =IF(ISNUMBER(Data!J21),Data!J21,"n/a") -> n/a | K21: =IF(AND(ISNUMBER(Data!J21),ISNUMBER(Data!K21)),IF(Data!J21>Data!K21,"▲",IF(Data!J21<Data!K21,"▼","↔")),"-") -> - | L21: =IF(ISNUMBER(Data!L21),Data!L21,"n/a") -> n/a | M21: =IF(AND(ISNUMBER(Data!L21),ISNUMBER(Data!M21)),IF(Data!L21>Data!M21,"▲",IF(Data!L21<Data!M21,"▼","↔")),"-") -> - | N21: =IF(ISNUMBER(Data!N21),Data!N21,"n/a") -> n/a | O21: =IF(AND(ISNUMBER(Data!N21),ISNUMBER(Data!O21)),IF(Data!N21>Data!O21,"▲",IF(Data!N21<Data!O21,"▼","↔")),"-") -> - | P21: =Data!P21 -> Monthly
A22: EXTERNAL | B22: Remittances – SL only (USD mn) | C22: USD mn | D22: — | E22: — | F22: — | G22: — | H22: — | I22: — | J22: — | K22: — | L22: — | M22: — | N22: =IF(ISNUMBER(Data!N22),Data!N22,"n/a") -> n/a | O22: =IF(AND(ISNUMBER(Data!N22),ISNUMBER(Data!O22)),IF(Data!N22>Data!O22,"▲",IF(Data!N22<Data!O22,"▼","↔")),"-") -> - | P22: =Data!P22 -> Monthly
A23: COMMODITY | B23: Brent Crude Oil (USD/bbl) | C23: USD/bbl | D23: =IF(ISNUMBER(Data!D23),Data!D23,"n/a") -> n/a | E23: =IF(AND(ISNUMBER(Data!D23),ISNUMBER(Data!E23)),IF(Data!D23>Data!E23,"▲",IF(Data!D23<Data!E23,"▼","↔")),"-") -> - | F23: =IF(ISNUMBER(Data!D23),Data!D23,"n/a") -> n/a | G23: =IF(AND(ISNUMBER(Data!D23),ISNUMBER(Data!E23)),IF(Data!D23>Data!E23,"▲",IF(Data!D23<Data!E23,"▼","↔")),"-") -> - | H23: =IF(ISNUMBER(Data!D23),Data!D23,"n/a") -> n/a | I23: =IF(AND(ISNUMBER(Data!D23),ISNUMBER(Data!E23)),IF(Data!D23>Data!E23,"▲",IF(Data!D23<Data!E23,"▼","↔")),"-") -> - | J23: =IF(ISNUMBER(Data!D23),Data!D23,"n/a") -> n/a | K23: =IF(AND(ISNUMBER(Data!D23),ISNUMBER(Data!E23)),IF(Data!D23>Data!E23,"▲",IF(Data!D23<Data!E23,"▼","↔")),"-") -> - | L23: =IF(ISNUMBER(Data!D23),Data!D23,"n/a") -> n/a | M23: =IF(AND(ISNUMBER(Data!D23),ISNUMBER(Data!E23)),IF(Data!D23>Data!E23,"▲",IF(Data!D23<Data!E23,"▼","↔")),"-") -> - | N23: =IF(ISNUMBER(Data!D23),Data!D23,"n/a") -> n/a | O23: =IF(AND(ISNUMBER(Data!D23),ISNUMBER(Data!E23)),IF(Data!D23>Data!E23,"▲",IF(Data!D23<Data!E23,"▼","↔")),"-") -> - | P23: =Data!P23 -> Weekly
A25: RAG LEGEND | B25: Green = Positive / On-target | C25: Amber = Caution / Near threshold | D25: Red = Negative / Breach | F25: ▲ = Rising vs prior period | G25: ▼ = Falling vs prior period | H25: ↔ = Unchanged | J25: n/a = No data yet. Enter values in the Data sheet to activate.
A27: SECTION KEY | B27: GROWTH | C27: GDP | Mfg PMI | Services PMI | Industrial Production
B28: INFLATION | C28: Headline CPI | Core CPI | Food Inflation
B29: MONETARY | C29: Policy Rate | 10Y Bond Yield | Yield Curve Slope
B30: LABOUR | C30: Unemployment Rate | Wage Growth
B31: MARKETS | C31: Equity Index (WoW%) | FX vs USD (WoW%) | Credit Spreads / CDS
B32: EXTERNAL | C32: Trade Balance | FX Reserves | SL Remittances
B33: COMMODITY | C33: Brent Crude Oil — global indicator applied to all countries

Sheet Data
A1: WEEKLY DATA ENTRY — LIVE VALUES & PRIOR PERIOD
A4: ID | B4: Indicator | C4: Unit | D4: UNITED STATES | E4: ▶ Prior (US) | F4: EURO AREA | G4: ▶ Prior (EUR) | H4: SINGAPORE | I4: ▶ Prior (SGP) | J4: CHINA | K4: ▶ Prior (CHN) | L4: INDIA | M4: ▶ Prior (IND) | N4: SRI LANKA | O4: ▶ Prior (LKR) | P4: Release Date | Q4: Week Ending
A5: G1 | B5: GDP Growth (YoY %) | C5: % YoY | P5: Quarterly
A6: G2 | B6: Manufacturing PMI | C6: Index | P6: Monthly (1st week)
A7: G3 | B7: Services PMI | C7: Index | P7: Monthly (1st week)
A8: G4 | B8: Industrial Production (YoY %) | C8: % YoY | P8: Monthly
A9: I1 | B9: Headline CPI (YoY %) | C9: % YoY | P9: Monthly (2nd week)
A10: I2 | B10: Core CPI (YoY %) | C10: % YoY | P10: Monthly
A11: I3 | B11: Food Inflation (YoY %) | C11: % YoY | P11: Monthly
A12: M1 | B12: Policy Rate (%) | C12: % | P12: Per meeting
A13: M2 | B13: 10Y Bond Yield (%) | C13: % | P13: Weekly (Friday)
A14: M3 | B14: Yield Curve (10Y−2Y, bps) | C14: bps | P14: Weekly
A15: L1 | B15: Unemployment Rate (%) | C15: % | P15: Monthly
A16: L2 | B16: Wage Growth (YoY %) | C16: % YoY | P16: Monthly/Quarterly
... A23: C1 | B23: Brent Crude (USD/bbl) | C23: USD/bbl | P23: Weekly

Sheet Indicators
A1: WEEKLY GLOBAL MACRO MONITOR — INDICATOR REFERENCE
A3: ID | B3: Category | C3: Indicator Name | D3: Description | E3: Unit | F3: Frequency | G3: RAG Logic (Green) | H3: RAG Logic (Amber) | I3: RAG Logic (Red) | J3: Bloomberg Ticker (US) | K3: Bloomberg Ticker (Euro Area) | L3: Bloomberg Ticker (Singapore) | M3: Bloomberg Ticker (China) | N3: Bloomberg Ticker (India) | O3: Bloomberg Ticker (Sri Lanka) | P3: Notes
A4: G1 | B4: Growth | C4: GDP Growth (YoY %) | D4: Real GDP, year-on-year % change (latest quarterly release) | E4: % YoY | F4: Quarterly | G4: >2.5% (DM); >5% (EM) | H4: 1–2.5% (DM); 3–5% (EM) | I4: <1% (DM); <3% (EM) or negative | J4: GDP CQOQ Index | K4: EUGNEMUQ Index | L4: SGDPYOY Index | M4: CNGDPYOY Index | N4: INGDPYOY Index | O4: SLGDPYOY Index | P4: Use Q/Q annualised for US; YoY for all others
A5: G2 | B5: Growth | C5: Manufacturing PMI | D5: S&P Global / ISM Manufacturing PMI; 50 = expansion/contraction threshold | E5: Index | F5: Monthly | G5: >52 and improving MoM | H5: 50–52 or stable | I5: <50 (contraction) | J5: MPMIUS Index | K5: MPMIDE Index | L5: MPMISI Index | M5: MPMICP Index | N5: MPMIIN Index | O5: MPMILK Index | P5: Monthly release; use S&P Global for comparability across all 6
A6: G3 | B6: Growth | C6: Services PMI | D6: S&P Global Services PMI; covers ~80% of GDP in most economies | E6: Index | F6: Monthly | G6: >52 and improving MoM | H6: 50–52 or stable | I6: <50 (contraction) | J6: MPMIUS Services Index | K6: MPMIEZ Services Index | L6: MPMISI Services Index | M6: MPMICP Services Index | N6: MPMIIN Services Index | O6: MPMILK Services Index | P6: Sri Lanka: use CBSL services index if PMI unavailable
A7: G4 | B7: Growth | C7: Industrial Production (YoY %) | D7: Manufacturing/industrial output, year-on-year % change | E7: % YoY | F7: Monthly | G7: >3% YoY | H7: 0–3% YoY | I7: <0% YoY (contraction) | J7: IP CHNG Index | K7: EUIPYOY Index | L7: SGIPYOY Index | M7: CNIPYOY Index | N7: INIPYOY Index | O7: SLIPYOY Index
A8: I1 | B8: Inflation | C8: Headline CPI (YoY %) | D8: Consumer Price Index, year-on-year % change | E8: % YoY | F8: Monthly | G8: Within 0.5pp of central bank target | H8: 0.5–2pp above/below target | I8: >2pp above target or deflationary | J8: CPI YOY Index | K8: ECCPEMUY Index | L8: SGCPIYOY Index | M8: CNCPIYOY Index | N8: INCPIYOY Index | O8: SLCPIYOY Index | P8: CB targets: US 2%, ECB 2%, MAS NEER, PBoC ~3%, RBI 4%, CBSL 5%
A9: I2 | B9: Inflation | C9: Core CPI (YoY %) | D9: CPI excluding food and energy, year-on-year % change | E9: % YoY | F9: Monthly | G9: Within 0.5pp of CB target | H9: 0.5–2pp above target | I9: >2pp above target or <0% | J9: CPI XYOY Index | K9: ECCPEXFE Index | L9: SGCORPYY Index | M9: CNCPICOY Index | N9: INCPIXFE Index | O9: SLCPICOR Index | P9: Better proxy of demand-driven inflation; key for monetary policy
A10: I3 | B10: Inflation | C10: Food Inflation (YoY %) | D10: Food component of CPI, YoY % change; especially relevant for Sri Lanka | E10: % YoY | F10: Monthly | G10: <5% YoY | H10: 5–10% YoY | I10: >10% YoY | J10: CPI FOOD Index | K10: ECCPFMUY Index | L10: SGCPIFOD Index | M10: CNCPIFOD Index | N10: INCPIFOD Index | O10: SLCPIFOD Index | P10: High weight in EM/SL basket; use FAO Food Price Index for global cross-check
A11: M1 | B11: Monetary Policy | C11: Policy Rate (%) | D11: Central bank benchmark/overnight rate; key monetary policy lever | E11: % | F11: As changed | G11: Rate on hold or cutting cycle | H11: Rate hiking pause; uncertain direction | I11: Active hiking cycle or emergency cut | J11: FEDL01 Index | K11: EURR002W Index | L11: SGPRIME Index | M11: CHIPON01 Index | N11: RIREPO Index | O11: CBSLPOLI Index | P11: Track direction of change (hiking/cutting/on hold) as much as level
A12: M2 | B12: Monetary Policy | C12: 10Y Government Bond Yield (%) | D12: 10-year sovereign bond yield; proxy for long-term financial conditions | E12: % | F12: Daily/Weekly | G12: Stable or declining WoW | H12: Rising but <20bps WoW | I12: >20bps rise WoW or inversion | J12: USGG10YR Index | K12: GDBR10 Index | L12: MASB10YR Index | M12: GCNY10YR Index | N12: GIND10YR Index | O12: GSLT10YR Index | P12: For SL: use secondary market T-bond yield (CBSL data)
A13: M3 | B13: Monetary Policy | C13: Yield Curve Slope (10Y − 2Y, bps) | D13: Difference between 10Y and 2Y sovereign yield; recession predictor when negative | E13: bps | F13: Weekly | G13: >50bps (normal/steep) | H13: 0–50bps (flat) | I13: <0bps (inverted — recession risk) | J13: USYC2Y10 Index | K13: GECU2Y10 Index | L13: MASC2Y10 Index | M13: GCNY2Y10 Index | N13: GIND2Y10 Index | O13: GSLT2Y10 Index | P13: Key early-warning indicator; inversion precedes recessions by ~12–18 months
A14: L1 | B14: Labour Market | C14: Unemployment Rate (%) | D14: Headline unemployment rate (ILO definition where available) | E14: % | F14: Monthly | G14: Falling or near structural low | H14: Rising but <1pp above cycle low | I14: Rising rapidly or >1pp above cycle low | J14: USURTOT Index | K14: UMRTEMU Index | L14: SGUETOTP Index | M14: CNUERATE Index | N14: INUETOTP Index | O14: SLUETOTP Index | P14: China reports urban survey rate; SL uses CBSL labour force survey
A15: L2 | B15: Labour Market | C15: Wage Growth (YoY %) | D15: Average hourly/weekly earnings or wage index, YoY % change | E15: % YoY | F15: Monthly | G15: 2–4% (real positive growth) | H15: >4% (above inflation; risk of wage-price spiral) | I15: <2% or negative real wages | J15: AHE YOY Index | K15: EUROSDEM Index | L15: SGWGIDX Index | M15: N/A (use Natl data) | N15: INWAGEYR Index | O15: SLWAGEYR Index | P15: Watch real wage growth (wage minus CPI) as consumer spending proxy
A16: F1 | B16: Financial Markets | C16: Equity Index (WoW % change) | D16: Benchmark equity index, week-on-week % price change | E16: % WoW | F16: Weekly | G16: >+1% WoW or positive YTD trend | H16: -1% to +1% WoW | I16: <-1% WoW or down >10% YTD | J16: SPX Index (S&P 500) | K16: SX5E Index (EuroStoxx 50) | L16: STI Index (Straits Times) | M16: SHCOMP Index (Shanghai) | N16: SENSEX Index (BSE) | O16: CSEALL Index (Colombo) | P16: Track both WoW change and YTD level vs 52W high
A17: F2 | B17: Financial Markets | C17: FX vs USD (WoW % change) | D17: Local currency per USD; WoW % change (positive = appreciation) | E17: % WoW | F17: Weekly | G17: Stable or appreciating (SL: LKR strengthening) | H17: -1% to 0% WoW depreciation | I17: >1% depreciation WoW or rapid slide | J17: DXY Index (USD basket) | K17: EURUSD Curncy | L17: USDSGD Curncy | M17: USDCNY Curncy | N17: USDINR Curncy | O17: USDLKR Curncy | P17: For US, use DXY index (USD strength vs basket). SL: LKR critical for inflation & debt
A18: F3 | B18: Financial Markets | C18: Credit Spreads / Risk Sentiment | D18: EM sovereign spreads (EMBI) or 5Y CDS spread as risk-off proxy | E18: bps | F18: Weekly | G18: Tightening or <300bps (EM EMBI) | H18: 300–600bps or widening moderately | I18: >600bps or widening rapidly | J18: JBCDCOMG Index (EMBI Global) | K18: JBCDCOMG Index | L18: ISDAS002 Curncy (5Y CDS SGD) | M18: CCHIN5Y1 CDS | N18: CISOV5Y1 CDS | O18: CSLNK5Y1 CDS | P18: SL 5Y CDS spread is key for IMF programme & market access monitoring
A19: E1 | B19: External Sector | C19: Trade Balance (USD bn) | D19: Exports minus imports (merchandise); monthly figure in USD bn | E19: USD bn | F19: Monthly | G19: Surplus or improving deficit trend | H19: Deficit stable / modest widening | I19: Rapidly widening deficit | J19: USTBTOT Index | K19: EUTRTOTL Index | L19: SGNXTRAD Index | M19: CNTBDLUS Index | N19: INTBDOLR Index | O19: SLTBDOLR Index | P19: For SL: also track export earnings & worker remittances separately
... A22: C1 | B22: Commodities | C22: Brent Crude Oil (USD/bbl) | D22: Front-month Brent crude futures; key for SL energy import costs & global inflation | E22: USD/bbl | F22: Weekly | G22: <$80/bbl or declining WoW | H22: $80–$100/bbl | I22: >$100/bbl or spiking | J22: CO1 Comdty | K22: CO1 Comdty | L22: CO1 Comdty | M22: CO1 Comdty | N22: CO1 Comdty | O22: CO1 Comdty | P22: Global indicator; same value all countries. SL imports ~100% of oil needs

Sheet Instructions
A1: RAG THRESHOLD LOGIC
A2: Indicator | B2: Green (Positive) | C2: Amber (Caution) | D2: Red (Negative) | E2: Rationale
A3: GDP Growth | B3: >=2.5% DM / >=5% EM | C3: 1-2.5% DM / 3-5% EM | D3: <1% DM or <3% EM; negative | E3: IMF defines stagnation below 1% for DM
A4: PMI (Mfg / Services) | B4: >=52 (expanding) | C4: 50-52 (neutral) | D4: <50 (contraction) | E4: 50 = expansion/contraction threshold
A5: CPI / Core CPI | B5: <=4% YoY | C5: 4-8% YoY | D5: >8% YoY | E5: CB targets: Fed/ECB 2%, RBI 4%, CBSL 5%
A6: Food Inflation | B6: <=5% | C6: 5-10% | D6: >10% | E6: Critical for EM social stability; high weight in SL CPI basket
A7: 10Y Bond Yield | B7: <=5% | C7: 5-7% | D7: >7% | E7: SL T-bond yields at 10Y+ are key IMF programme monitor
A8: Yield Curve (10Y-2Y) | B8: >=50 bps (steep) | C8: 0-50 bps (flat) | D8: <0 bps (inverted) | E8: Inverted curve is a leading recession indicator (~12-18M lead)
A9: Unemployment Rate | B9: <=5% | C9: 5-7% | D9: >7% | E9: Track direction more than level; varies by structural unemployment
A10: Equity / FX (WoW %) | B10: Equity >=1% / FX >=0% | C10: -1% to +1% | D10: Equity <-1% / FX <-1% | E10: FX: positive = local currency appreciation vs USD
A11: Credit Spreads / CDS | B11: <=300 bps | C11: 300-600 bps | D11: >600 bps | E11: SL CDS spread monitored for IMF programme continuity
A12: Brent Crude (USD/bbl) | B12: <=80 | C12: 80-100 | D12: >100 | E12: SL imports 100% of oil; high oil = fiscal and inflation risk
A14: DATA SOURCES FOR MANUAL ENTRY
A15: Sri Lanka (GDP, CPI, Trade, Reserves, Remittances): | B15: Central Bank of Sri Lanka (CBSL): cbsl.gov.lk/statistics
A16: Singapore Wages: | B16: Ministry of Manpower (MOM): mom.gov.sg/statistics
A17: China Wages: | B17: National Bureau of Statistics (NBS): stats.gov.cn
A18: Global PMI (all 6 countries): | B18: S&P Global PMI releases: published 1st business day of each month
A20: VERSION HISTORY
A21: v1.0 | B21: Initial build: 6 countries, 19 indicators, 6 categories, Bloomberg BDP formulas, RAG conditional formatting. | C21: 46174
